cheera/__init__.py
cheera-0.0.2.dist-info/METADATA
cheera-0.0.2.dist-info/WHEEL
cheera-0.0.2.dist-info/top_level.txt
cheera-0.0.2.dist-info/RECORD
